arize_mcp/__init__.py
arize_mcp/__main__.py
arize_mcp/arize_mcp.py
arize_mcp/version.py
arize_mcp/refs/advanced_tracing_docs/tracing_summary_python.md
arize_mcp/refs/advanced_tracing_docs/tracing_summary_typescript.md
arize_mcp/refs/auto_inst_examples/arize/agno/python.md
arize_mcp/refs/auto_inst_examples/arize/amazon-bedrock/python.md
arize_mcp/refs/auto_inst_examples/arize/anthropic/python.md
arize_mcp/refs/auto_inst_examples/arize/autogen/python.md
arize_mcp/refs/auto_inst_examples/arize/beeai/javascript.md
arize_mcp/refs/auto_inst_examples/arize/crewai/python.md
arize_mcp/refs/auto_inst_examples/arize/dspy/python.md
arize_mcp/refs/auto_inst_examples/arize/google-gen-ai/python.md
arize_mcp/refs/auto_inst_examples/arize/groq/python.md
arize_mcp/refs/auto_inst_examples/arize/guardrails-ai/python.md
arize_mcp/refs/auto_inst_examples/arize/haystack/python.md
arize_mcp/refs/auto_inst_examples/arize/hugging-face-smolagents/python.md
arize_mcp/refs/auto_inst_examples/arize/instructor/python.md
arize_mcp/refs/auto_inst_examples/arize/langchain/python.md
arize_mcp/refs/auto_inst_examples/arize/langchain/typescript.md
arize_mcp/refs/auto_inst_examples/arize/langflow/python.md
arize_mcp/refs/auto_inst_examples/arize/langgraph/python.md
arize_mcp/refs/auto_inst_examples/arize/litellm/python.md
arize_mcp/refs/auto_inst_examples/arize/llamaindex/python.md
arize_mcp/refs/auto_inst_examples/arize/mistralai/python.md
arize_mcp/refs/auto_inst_examples/arize/model-context-protocol/python.md
arize_mcp/refs/auto_inst_examples/arize/openai/javascript.md
arize_mcp/refs/auto_inst_examples/arize/openai/python.md
arize_mcp/refs/auto_inst_examples/arize/openai-agents/python.md
arize_mcp/refs/auto_inst_examples/arize/prompt-flow/python.md
arize_mcp/refs/auto_inst_examples/arize/pydantic-ai/python.md
arize_mcp/refs/auto_inst_examples/arize/together/python.md
arize_mcp/refs/auto_inst_examples/arize/vercel/typescript.md
arize_mcp/refs/auto_inst_examples/arize/vertexai/python.md
arize_tracing_assistant-0.2.12.dist-info/METADATA
arize_tracing_assistant-0.2.12.dist-info/WHEEL
arize_tracing_assistant-0.2.12.dist-info/entry_points.txt
arize_tracing_assistant-0.2.12.dist-info/licenses/LICENSE
arize_tracing_assistant-0.2.12.dist-info/RECORD
