Metadata-Version: 2.4
Name: arize-tracing-assistant
Version: 0.2.12
Summary: Arize tracing assistant
Project-URL: Documentation, https://arize.com/docs/ax/observe/quickstart-llm
Author-email: Arize AI <support@arize.com>
Maintainer-email: Arize AI <support@arize.com>
License-Expression: BSD-2-Clause
License-File: LICENSE
Keywords: Explainability,Monitoring,Observability,Tracing
Classifier: Development Status :: 5 - Production/Stable
Classifier: Intended Audience :: Developers
Classifier: Programming Language :: Python
Classifier: Programming Language :: Python :: 3.10
Classifier: Programming Language :: Python :: 3.11
Classifier: Programming Language :: Python :: 3.12
Classifier: Topic :: Scientific/Engineering :: Artificial Intelligence
Classifier: Topic :: Software Development :: Libraries :: Python Modules
Classifier: Topic :: System :: Logging
Classifier: Topic :: System :: Monitoring
Requires-Python: >=3.10
Requires-Dist: mcp[cli]>=1.9.0
Requires-Dist: requests>=2.32.3
